citext/__init__.py
citext/_version.py
citext/apps.py
citext/baker_generators.py
citext/fields.py
citext/lookups.py
django_citext-1.0.2.dist-info/LICENSE
django_citext-1.0.2.dist-info/WHEEL
django_citext-1.0.2.dist-info/METADATA
django_citext-1.0.2.dist-info/RECORD
